Workbook

Sheet 01.2026
A1: LIQUIDACION DE GASTOS
A2: MES DE LIQUIDACIÓN (CIERRE): ENERO 2026 MES DE VENCIMIENTO DE LA LIQUIDACION: FEBRERO 2026
A3: ADMINISTRACIÓN CONSORCIO D&F Administracion SARMIENTO 356,358,360 CUIT: 27-25108998-7 CUIT: 30-71412062-6 Matricula: RPAC N° 1772 / RPA N° 17517 SARMIENTO 356 -360 - Lomas de Zamora (Bs. As.) Telefonos: 4742-6085 / 1167867049 / 1168939477 CLAVE SUTERH: Bynnon 1686 - Adrogue (1846) Mail: dyfadmconsorcios@gmail.com
A4: Estado de cuentas y prorrateo PERIODO ENERO 2025 VENCIMIENTO 15/02/2026 Tasa de interés: 7,80%
A5: UF | B5: DEPTO | C5: PROPIETARIOS | D5: PORCENTUAL | E5: SALDO ANTERIOR | F5: PAGOS | G5: SALDO
A6: 1 | B6: 1°A - 356 | C6: SEVERINO | D6: 0.0156 | E6: 353035 | F6: 350050 | G6: 2985
A7: 2 | B7: 1°C - 356 | C7: FERNANDEZ | D7: 0.0107 | E7: 251585 | F7: 251585 | G7: $ -
A8: 3 | B8: 1°B - 356 | C8: ALVAREZ MARIA INES | D8: 0.0103 | E8: 243304 | F8: 243304 | G8: $ -
A9: 4 | B9: 1°A - 360 | C9: PERRI | D9: 0.0103 | E9: 243304 | F9: 243304 | G9: $ -
A10: 5 | B10: 1°C - 360 | C10: BONFANTI SANDRA | D10: 0.0114 | E10: 266078 | F10: 266078 | G10: $ -
A11: 6 | B11: 1°B - 360 | C11: MAGLIOLO SILVIA | D11: 0.0172 | E11: 386161 | F11: 386161 | G11: $ -
A12: 7 | B12: 2°A - 356 | C12: MALDAJAN | D12: 0.016 | E12: 654057 | F12: $ - | G12: 654057
A13: 8 | B13: 2°C - 356 | C13: CARROSO | D13: 0.0109 | E13: 255726 | F13: 255726 | G13: $ -
A14: 9 | B14: 2°B - 356 | C14: BLAUSTEIN | D14: 0.0103 | E14: 243304 | F14: 243304 | G14: $ -
A15: 10 | B15: 2°A - 360 | C15: LOPARDO | D15: 0.0102 | E15: 241233 | F15: 241233 | G15: $ -
A16: 11 | B16: 2°C - 360 | C16: MENA | D16: 0.0107 | E16: 251585 | F16: 251585 | G16: $ -
A17: 12 | B17: 2°B - 360 | C17: PUMA ROSA | D17: 0.0155 | E17: 350964 | F17: 350964 | G17: $ -
A18: 13 | B18: 3°A - 356 | C18: GRIMM | D18: 0.0159 | E18: 359246 | F18: 359246 | G18: $ -
A19: 14 | B19: 3°C - 356 | C19: GRIMM | D19: 0.0107 | E19: 251621 | F19: 251621 | G19: $ -
A20: 15 | B20: 3°B - 356 | C20: FERNANDEZ | D20: 0.0102 | E20: 241233 | F20: 241233 | G20: $ -
A21: 16 | B21: 3°A - 360 | C21: IANELLO | D21: 0.0103 | E21: 243304 | F21: 243304 | G21: $ -
A22: 17 | B22: 3°C - 360 | C22: MUSACCHIO | D22: 0.0125 | E22: 509762 | F22: 509762 | G22: $ -
A23: 18 | B23: 3°B - 360 | C23: ROMBOUTS DIETER | D23: 0.0155 | E23: 350964 | F23: 350964 | G23: $ -
A24: 19 | B24: 4°A - 356 | C24: RIONEGRO CARLOS ALBERTO | D24: 0.0171 | E24: 384091 | F24: 384091 | G24: $ -
A25: 20 | B25: 4°C - 356 | C25: GIANOLA | D25: 0.0107 | E25: 251585 | F25: 251585 | G25: $ -
A26: 21 | B26: 4°B - 356 | C26: FRANCO | D26: 0.0119 | E26: 276430 | F26: $ - | G26: 276430
A27: 22 | B27: 4°A - 360 | C27: DOMINGUEZ OSVALDO | D27: 0.0119 | E27: 276430 | F27: 276430 | G27: $ -
A28: 23 | B28: 4°C - 360 | C28: CALANDRA | D28: 0.0124 | E28: 286782 | F28: 286782 | G28: $ -
A29: 24 | B29: 4°B - 360 | C29: TAKEDA LAURA NANCY | D29: 0.0156 | E29: 353035 | F29: 353035 | G29: $ -
A30: 25 | B30: 5°A - 356 | C30: SUAREZ PATRICIO | D30: 0.0156 | E30: 353035 | F30: 353100 | G30: -65
A31: 26 | B31: 5°C - 356 | C31: LANATI | D31: 0.0108 | E31: 231086 | F31: 137318 | G31: 93768
A32: 27 | B32: 5°B - 356 | C32: NIBALI AGUSTINA DENISE | D32: 0.0102 | E32: 241233 | F32: 241233 | G32: $ -
A33: 28 | B33: 5°A - 360 | C33: FLOLASCO SILVINA | D33: 0.0102 | E33: 241233 | F33: 241233 | G33: $ -
A34: 29 | B34: 5°C - 360 | C34: PUMAR RICARDO | D34: 0.0112 | E34: 261937 | F34: 261937 | G34: $ -
A35: 30 | B35: 5°B - 360 | C35: JAIMES MARISA | D35: 0.0175 | E35: 392372 | F35: 392372 | G35: $ -
A36: 31 | B36: 6°A - 356 | C36: FIORENZA ROSARIO | D36: 0.0227 | E36: 500033 | F36: 500033 | G36: $ -
A37: 32 | B37: 6°C - 356 | C37: JUIZ K | D37: 0.0123 | E37: 284712 | F37: 284712 | G37: $ -
A38: 33 | B38: 6°B - 356 | C38: DELGADO | D38: 0.0118 | E38: 274360 | F38: 274360 | G38: $ -
A39: 34 | B39: 6°A - 360 | C39: IGLESIAS | D39: 0.0139 | E39: 317839 | F39: $ - | G39: 317839
A40: 35 | B40: 6°C - 360 | C40: FAPSA | D40: 0.0123 | E40: 284712 | F40: 284712 | G40: $ -
A41: 36 | B41: 6°B - 360 | C41: GIANCASPRO | D41: 0.0157 | E41: 355105 | F41: 355105 | G41: $ -
A42: 37 | B42: 7°A - 356 | C42: FIORENZA ROSARIO | D42: 0.0155 | E42: 350964 | F42: 350964 | G42: $ -
A43: 38 | B43: 7°C - 356 | C43: ANTON RICARDO ENRIQUE | D43: 0.0114 | E43: 266078 | F43: 266078 | G43: $ -
A44: 39 | B44: 7°B - 356 | C44: FRANQUEIRA | D44: 0.0103 | E44: 243304 | F44: 243304 | G44: $ -
A45: 40 | B45: 7°A - 360 | C45: BAL MARICEL | D45: 0.0106 | E45: 249515 | F45: 249515 | G45: $ -
A46: 41 | B46: 7°C - 360 | C46: CASTRO | D46: 0.0108 | E46: 448907 | F46: 448507 | G46: 400
A47: 42 | B47: 7°B - 360 | C47: DEL RIO ANDREA | D47: 0.0161 | E47: 363387 | F47: 363387 | G47: $ -
A48: 43 | B48: 8°A - 356 | C48: SIMON PABLO | D48: 0.0192 | E48: 426616 | F48: 427000 | G48: -384
A49: 44 | B49: 8°C - 356 | C49: RAAD J. F. | D49: 0.0123 | E49: 284712 | F49: 284712 | G49: $ -
A50: 45 | B50: 8°B - 356 | C50: PONZIO FACUNDO TOMAS | D50: 0.0108 | E50: 253656 | F50: 253656 | G50: $ -
A51: 46 | B51: 8°A - 360 | C51: DURRUTY - VAZQUEZ | D51: 0.0119 | E51: 276430 | F51: 276430 | G51: $ -
A52: 47 | B52: 8°C - 360 | C52: CICCONE-ROSSI | D52: 0.0138 | E52: 781902 | F52: 781902 | G52: $ -
A53: 48 | B53: 8°B - 360 | C53: MALLAMACE MARTA | D53: 0.0155 | E53: 350964 | F53: 350964 | G53: $ -
A54: 49 | B54: 9°A - 356 | C54: CALONGE RICARDO | D54: 0.0191 | E54: 360498 | F54: 390498 | G54: -2030000
A55: 50 | B55: 9°B - 356 | C55: TOSAR | D55: 0.0117 | E55: 272289 | F55: 272289 | G55: $ -
A56: 51 | B56: 9°A - 360 | C56: FAPSA | D56: 0.0117 | E56: 271622 | F56: 272000 | G56: -378
A57: 52 | B57: 9°B - 360 | C57: FAPSA | D57: 0.0197 | E57: 437921 | F57: 437921 | G57: $ -
A58: 53 | B58: 10°A - 356 | C58: RICCI - ROLDAN | D58: 0.0186 | E58: 415147 | F58: 415147 | G58: $ -
A59: 54 | B59: 10°B - 356 | C59: PRIMAVERA | D59: 0.0102 | E59: 241233 | F59: $ - | G59: 241233
A60: 55 | B60: 10°A - 360 | C60: MARTYNIUK | D60: 0.0102 | E60: 241233 | F60: 241233 | G60: $ -
A61: 56 | B61: 10°B - 360 | C61: GINES DEBORA | D61: 0.0172 | E61: 386161 | F61: 386161 | G61: $ -
A62: 57 | B62: 11°A - 356 | C62: ASSETTA ANA MARIA | D62: 0.0193 | E62: 429639 | F62: 429639 | G62: $ -
A63: 58 | B63: 11°B - 356 | C63: PRIMAVERA | D63: 0.0105 | E63: 247445 | F63: 247445 | G63: $ -
A64: 59 | B64: 11°A - 360 | C64: MARTYNIUK | D64: 0.0103 | E64: 243304 | F64: 243304 | G64: $ -
A65: 60 | B65: 11°B - 360 | C65: VILLAR | D65: 0.0186 | E65: 1591606 | F65: 415147 | G65: 1176459
A66: 61 | B66: 12°A - 356 | C66: FERNANDEZ | D66: 0.0176 | E66: 394443 | F66: 394443 | G66: $ -
A67: 62 | B67: 12°B - 356 | C67: LAGANA OSCAR | D67: 0.0103 | E67: 243304 | F67: 243304 | G67: $ -
A68: 63 | B68: 12°A - 360 | C68: VILELA | D68: 0.0102 | E68: 241233 | F68: 241233 | G68: $ -
A69: 64 | B69: 12°B - 360 | C69: MARTINIELLO | D69: 0.0193 | E69: 429639 | F69: 429639 | G69: $ -
A70: 65 | B70: 13°A - 356 | C70: GAVELINI FEDERICO | D70: 0.0173 | E70: 388232 | F70: 388232 | G70: $ -
A71: 66 | B71: 13°B - 356 | C71: SEDAME | D71: 0.0102 | E71: 241233 | F71: 241233 | G71: $ -
A72: 67 | B72: 13°A - 360 | C72: BRUNO SANDRA | D72: 0.0102 | E72: 241233 | F72: 241233 | G72: $ -
A73: 68 | B73: 13°B - 360 | C73: QUENARDELLE | D73: 0.0169 | E73: 379950 | F73: 379950 | G73: $ -
A74: 69 | B74: 14°A - 356 | C74: VELAYOS CELINA | D74: 0.0413 | E74: 885127 | F74: 885127 | G74: $ -
A75: 70 | B75: 14°A - 360 | C75: STEVEN PUTZ | D75: 0.0413 | E75: 885126 | F75: 885126 | G75: $ -
C76: TOTALES | D76: 0.9979 | E76: 25026535 | F76: 22294190 | G76: 732345
A79: Estado de propietarios morosos
A80: UF | B80: DEPTO | C80: CONSORCISTA | D80: DEUDA
A81: 7 | B81: 2°A - 356 | C81: MALDAJAN | D81: 292741
A82: 14 | B82: 3°C - 356 | C82: GRIMM | D82: 35
A83: 17 | B83: 3°C - 360 | C83: MUSACCHIO | D83: 220909
A84: 41 | B84: 7°C - 360 | C84: CASTRO | D84: 195251
A85: 47 | B85: 8°C - 360 | C85: CICCONE-ROSSI | D85: 466135
A86: 60 | B86: 11°B - 360 | C86: VILLAR | D86: 1176460
C87: TOTAL | D87: 2351531
A90: GASTOS ORDINARIOS DEL PERÍODO (SUMINISTROS, SERVICIOS, ABONOS Y SEGUROS)
A91: REMUNERACIONES DEL PERSONAL | E91: GASTOS COMUNES | I91: % DEL GASTO TOTAL
A92: BUSTAMANTE JUAN MANUEL - ENCARGADO PERMANTENTE SIN VIVIENDA 4ta CATEGORIA.
A93: CUIL: 20-13606437-2 - MES LIQUIDADO: ENERO 2026
A95: SUELDO/ JORNAL | C95: 906864.19
A96: ANTIGÜEDAD | C96: 224902.8
A97: AJUSTE SAC 2do SEMESTRE | C97: 120000
A98: FERIADO | C98: 37483.72
A99: RETIRO DE RESIDUOS | C99: 120820
A100: PLUS LIMPIEZA COCHERA | C100: 23553.4
A101: PLUS JARDIN | C101: 23553.4
A102: VIATICOS | C102: 65596.5
A103: JUBILACION 11% | D103: 167505.14
A104: INSSJP 3% | D104: 45683.22
A105: OBRA SOCIAL 3 % | D105: 45683.22
...

Sheet CUOTA SINDICAL

Sheet COMISIONES

Sheet 25413

Sheet LA UNION E HIJOS
A1: FECHA PAGO | B1: MONTO
A2: 46386 | B2: 22895.81 | C2: CON FACTURA
A3: 46386 | B3: 23598.23 | C3: CON FACTURA
A4: 46386 | B4: 24361.2 | C4: CON FACTURA
A5: 46386 | B5: 520591.32 | C5: CON FACTURA
A6: 46386 | B6: 769264.83 | C6: CON FACTURA
A7: LIQUIDADO DICIEMBRE | B7: =SUM(B2:B6) -> 1360711.4

Sheet DIFERENCIAS ENCONTRADAS
A1: DIFERENCIAS ENTRE LO LOQUIDADO Y LO REALMENTE ABONADO
A2: FECHA | B2: DETALLE | C2: PAGO REALIZADO | D2: EN LIQUIDACIÓN | E2: DIF | F2: OBSERVACION
A3: 46361 | B3: SUELDO JUAN | C3: ='12.2025'!L113 -> #REF! | D3: 1089415 | E3: =C3-D3 -> #REF! | F3: IMPORTE DEVENGADO NO REAL (LIQUIDACION MES ANTERIOR $ 1,054,813.41)
A4: 46361 | B4: SUELDO JAVIER | C4: ='12.2025'!L132 -> #REF! | D4: 681302 | E4: =C4-D4 -> #REF! | F4: IMPORTE DEVENGADO NO REAL (LIQUIDACION MES ANTERIOR $ 662,491.25) SE DEPOSITARON 20000 DE MAS
A5: 46361 | B5: SUELDO RAMIREZ | C5: ='12.2025'!L148 -> #REF! | D5: 688435 | E5: =C5-D5 -> #REF! | F5: IMPORTE DEVENGADO NO REAL (LIQUIDACION MES ANTERIOR $ 745,574.00) SE DEPOSITARON 58023 DE MENOS
A6: 46374 | B6: AGUINALDO JUAN | C6: ='12.2025'!L114 -> #REF! | D6: 1287347 | E6: =C6-D6 -> #REF! | F6: IMPORTE LIQUIDADO EN EL MES ANTERIOR CON PROVISION TOTAL MENOR AL REAL - AUNQUE EL PAGO CORRESPONDE LA RECAUDACION FUE MENOR
A7: 46374 | B7: AGUINALDO JAVIER | C7: ='12.2025'!L133 -> #REF! | D7: 0 | E7: =C7-D7 -> #REF! | F7: IMPORTE LIQUIDADO EN EL MES ANTERIOR CON PROVISION TOTAL MENOR AL REAL - AUNQUE EL PAGO CORRESPONDE LA RECAUDACION FUE MENOR
A8: 46374 | B8: AGUINALDO RAMIREZ | C8: ='12.2025'!L149 -> #REF! | D8: 0 | E8: =C8-D8 -> #REF! | F8: IMPORTE LIQUIDADO EN EL MES ANTERIOR CON PROVISION TOTAL MENOR AL REAL - AUNQUE EL PAGO CORRESPONDE LA RECAUDACION FUE MENOR
A9: 46368 | B9: CARGAS SOCIALES | C9: ='12.2025'!L153 -> #REF! | D9: ='12.2025'!F153 -> #REF! | E9: =C9-D9 -> #REF! | F9: IMPORTE DEVENGADO NO REAL (LIQUIDACION MES ANTERIOR $ 1,546,772.50)
A10: 46368 | B10: FED ARG DE TRAB | C10: 15578.92 | D10: 679584.04 | E10: =C10-D10 -> -664005.12 | F10: IMPORTE DEVENGADO NO REAL (LIQUIDACION MES ANTERIOR CON COMPROBANTES EN EL MES ANTERIOR)
A11: 46368 | B11: SIND UN TRAB REN | C11: 140210.29 | D11: 0 | E11: =C11-D11 -> 140210.29 | F11: IMPORTE DEVENGADO NO REAL (LIQUIDACION MES ANTERIOR CON COMPROBANTES EN EL MES ANTERIOR)
A12: 46368 | B12: FED ARG TRAB REN | C12: 255053.93 | D12: 0 | E12: =C12-D12 -> 255053.93 | F12: IMPORTE DEVENGADO NO REAL (LIQUIDACION MES ANTERIOR CON COMPROBANTES EN EL MES ANTERIOR)
A13: LA UNION E HIJOS SRL | B13: COMPRA DE PINTURA CUOATA 01/02 | C13: 1360711.4 | D13: 3500000 | E13: =C13-D13 -> -2139288.6 | F13: SE LIQUIDO UN GASTO EXTRAORDINARIO MUY SUPERIOR A LO FINALMENTE FACTURADO Y ESTA RECAUDACIÓN NO FUE INCLUIDA EN EL RESUMEN DE FDR QUE IBAN DESTINADOS A PINTURA, MIENTRAS QUE LOS GASTOS SI ESTAN DETALLADOS.
A14: 46368 | B14: CLEANNIG SERVICE - MATERIALES DE LIMPIEZA | C14: 175845 | D14: 212900 | E14: =C14-D14 -> -37055 | F14: SEGUN ESTO SE ABONO POR MENOS, AUNQUE EL COMPROBANTE NO ES VÁLIDO COMO FACTURA. TENEMOS LA FACTURA?
A15: 46361 | B15: SEGURIDAD NOVIEMBRE 2025 FACTURA N° 00002-0044 | C15: 2372281.2 | D15: 3704325 | E15: =D15-C15 -> 1332043.8 | F15: IMPORTE DEVENGADO NO REAL (LIQUIDACION MES ANTERIOR CON COMPROBANTES EN EL MES ANTERIOR)
A17: LIQUIDADO SIN PAGO REGISTRADO EN CUENTA
A18: YPF CICLOS | B18: COMPRA DE COMBUSTIBLE FACT Nro 00011-53269 | C18: 32000.04 | D18: COMPROBANTE CON FECHA 14/10 21:25
A19: YPF CICLOS | B19: COMPRA DE COMBUTIBLR FACT.Nro 0001-53270 | C19: 32000.04 | D19: COMPROBANTE CON FECHA 14/10 21:27
A20: ASCENSORES GUILLEMI | B20: Mantenimiento ascensores DICIEMBRE | C20: 87866.77 | D20: FACTURA DE 120000 FECHA 5/1
A21: FOTOCOPIAS DE EXPENSAS NOVIEMBRE | C21: 18900 | D21: SIN COMPROBANTE
A23: PAGO REGISTRADOS QUE NO FIGURAN EN ESTRACTO Y SI CONSIDERA LA ADMINISTRACIÓN
B24: CALOGNE RICARDO | C24: 9°A - 356 | D24: 65000
A26: GASTOS NO LIQUIDADOS QUE FUERON DEBITADOS DE CUENTA
A27: 46361 | B27: RAFAEL MOREL ROMAN | C27: 700000 | D27: CON RECIBI FECHA 5/12 | E27: PUESTO EN ESE RESUMEN DE FDR MAL COMPUTADO
A28: 46368 | B28: LUIS DE LA PAS PAVON | C28: 160000 | D28: SIN NINGUN COMPROBANTE EN ESTE MES | E28: ENTIENDO QUE PAGARON LA DIFERENCIA LIQUIDADA EL MES PASADO EN ESTE MES SALDANDO EL ERROR MARCADO EL MES ANTERIOR
A29: 46368 | B29: RAFAEL MOREL ROMAN | C29: 1000000 | D29: CON RECIBI FECHA 12/12 | E29: PUESTO EN ESE RESUMEN DE FDR MAL COMPUTADO
A30: 46374 | B30: RAFAEL MOREL ROMAN | C30: 1700000 | D30: CON RECIBI FECHA 18/12 | E30: PUESTO EN ESE RESUMEN DE FDR MAL COMPUTADO
A31: 46378 | B31: RAFAEL MOREL ROMAN | C31: 1500000 | D31: CON RECIBI FECHA 29/12 | E31: PUESTO EN ESE RESUMEN DE FDR MAL COMPUTADO
