Workbook

Sheet 02.2026
A1: LIQUIDACION DE GASTOS
A2: MES DE LIQUIDACIÓN (CIERRE): FEBRERO 2026 MES DE VENCIMIENTO DE LA LIQUIDACION: MARZO 2026
A3: ADMINISTRACIÓN CONSORCIO D&F Administracion SARMIENTO 356,358,360 CUIT: 27-25108998-7 CUIT: 30-71412062-6 Matricula: RPAC N° 1772 / RPA N° 17517 SARMIENTO 356 -360 - Lomas de Zamora (Bs. As.) Telefonos: 4742-6085 / 1167867049 / 1168939477 CLAVE SUTERH: Bynnon 1686 - Adrogue (1846) Mail: dyfadmconsorcios@gmail.com
A4: Estado de cuentas y prorrateo PERIODO FEBRERO 2025 VENCIMIENTO 15/03/2026 | S4: Tasa de interés: 7,90%
A5: UF | B5: DEPTO | C5: PROPIETARIOS | D5: PORCENTUAL | E5: SALDO ANTERIOR | G5: PAGOS | I5: SALDO
A6: 1 | B6: 1°A - 356 | C6: SEVERINO | D6: 0.0156 | E6: 393470 | G6: 392000 | I6: 1470
A7: 2 | B7: 1°C - 356 | C7: FERNANDEZ | D7: 0.0107 | E7: 287636 | G7: 287636 | I7: $ -
A8: 3 | B8: 1°B - 356 | C8: ALVAREZ MARIA INES | D8: 0.0103 | E8: 279259 | G8: 279259 | I8: $ -
A9: 4 | B9: 1°A - 360 | C9: PERRI | D9: 0.0103 | E9: 279259 | G9: 279259 | I9: $ -
A10: 5 | B10: 1°C - 360 | C10: BONFANTI SANDRA | D10: 0.0114 | E10: 302295 | G10: 300000 | I10: 2295
A11: 6 | B11: 1°B - 360 | C11: MAGLIOLO SILVIA | D11: 0.0172 | E11: 423761 | G11: 423761 | I11: $ -
A12: 7 | B12: 2°A - 356 | C12: MALDAJAN | D12: 0.016 | E12: 1103703 | G12: 1104000 | I12: -297
A13: 8 | B13: 2°C - 356 | C13: CARROSO | D13: 0.0109 | E13: 291824 | G13: 291824 | I13: $ -
A14: 9 | B14: 2°B - 356 | C14: BLAUSTEIN | D14: 0.0103 | E14: 279259 | G14: 279259 | I14: $ -
A15: 10 | B15: 2°A - 360 | C15: LOPARDO | D15: 0.0102 | E15: 277164 | G15: 277164 | I15: $ -
A16: 11 | B16: 2°C - 360 | C16: MENA | D16: 0.0107 | E16: 287636 | G16: 287636 | I16: $ -
A17: 12 | B17: 2°B - 360 | C17: PUMA ROSA | D17: 0.0155 | E17: 388159 | G17: 388159 | I17: $ -
A18: 13 | B18: 3°A - 356 | C18: GRIMM | D18: 0.0159 | E18: 396536 | G18: 396536 | I18: $ -
A19: 14 | B19: 3°C - 356 | C19: GRIMM | D19: 0.0107 | E19: 287636 | G19: 287636 | I19: $ -
A20: 15 | B20: 3°B - 356 | C20: FERNANDEZ | D20: 0.0102 | E20: 277164 | G20: 277164 | I20: $ -
A21: 16 | B21: 3°A - 360 | C21: IANELLO | D21: 0.0103 | E21: 279259 | G21: 279259 | I21: $ -
A22: 17 | B22: 3°C - 360 | C22: MUSACCHIO | D22: 0.0125 | E22: 325332 | G22: $ - | I22: 325332
A23: 18 | B23: 3°B - 360 | C23: ROMBOUTS DIETER | D23: 0.0155 | E23: 388159 | G23: 388159 | I23: $ -
A24: 19 | B24: 4°A - 356 | C24: RIONEGRO CARLOS ALBERTO | D24: 0.0171 | E24: 421666 | G24: 421666 | I24: $ -
A25: 20 | B25: 4°C - 356 | C25: GIANOLA | D25: 0.0107 | E25: 287636 | G25: 287636 | I25: $ -
A26: 21 | B26: 4°B - 356 | C26: FRANCO | D26: 0.0119 | E26: 610758 | G26: 610758 | I26: $ -
A27: 22 | B27: 4°A - 360 | C27: DOMINGUEZ OSVALDO | D27: 0.0119 | E27: 312766 | G27: 312766 | I27: $ -
A28: 23 | B28: 4°C - 360 | C28: CALANDRA | D28: 0.0124 | E28: 323237 | G28: 323237 | I28: $ -
A29: 24 | B29: 4°B - 360 | C29: TAKEDA LAURA NANCY | D29: 0.0156 | E29: 390253 | G29: 390253 | I29: $ -
A30: 25 | B30: 5°A - 356 | C30: SUAREZ PATRICIO | D30: 0.0156 | E30: 390188 | G30: 390188 | I30: $ -
A31: 26 | B31: 5°C - 356 | C31: LANATI | D31: 0.0108 | E31: 390812 | G31: $ - | I31: 390812
A32: 27 | B32: 5°B - 356 | C32: NIBALI AGUSTINA DENISE | D32: 0.0102 | E32: 277164 | G32: 277164 | I32: $ -
A33: 28 | B33: 5°A - 360 | C33: FLOLASCO SILVINA | D33: 0.0102 | E33: 277164 | G33: 277164 | I33: $ -
A34: 29 | B34: 5°C - 360 | C34: PUMAR RICARDO | D34: 0.0112 | E34: 298107 | G34: 298107 | I34: $ -
A35: 30 | B35: 5°B - 360 | C35: JAIMES MARISA | D35: 0.0175 | E35: 430043 | G35: $ - | I35: 430043
A36: 31 | B36: 6°A - 356 | C36: FIORENZA ROSARIO | D36: 0.0227 | E36: 538943 | G36: 538943 | I36: $ -
A37: 32 | B37: 6°C - 356 | C37: JUIZ K | D37: 0.0123 | E37: 321143 | G37: 321143 | I37: $ -
A38: 33 | B38: 6°B - 356 | C38: DELGADO | D38: 0.0118 | E38: 310672 | G38: 310672 | I38: $ -
A39: 34 | B39: 6°A - 360 | C39: IGLESIAS | D39: 0.0139 | E39: 697281 | G39: 697281 | I39: $ -
A40: 35 | B40: 6°C - 360 | C40: FAPSA | D40: 0.0123 | E40: 321143 | G40: 321143 | I40: $ -
A41: 36 | B41: 6°B - 360 | C41: GIANCASPRO | D41: 0.0157 | E41: 392347 | G41: 392347 | I41: $ -
A42: 37 | B42: 7°A - 356 | C42: FIORENZA ROSARIO | D42: 0.0155 | E42: 388159 | G42: 388159 | I42: $ -
A43: 38 | B43: 7°C - 356 | C43: ANTON RICARDO ENRIQUE | D43: 0.0114 | E43: 302295 | G43: 302295 | I43: $ -
A44: 39 | B44: 7°B - 356 | C44: FRANQUEIRA | D44: 0.0103 | E44: 279259 | G44: 279259 | I44: $ -
A45: 40 | B45: 7°A - 360 | C45: BAL MARICEL | D45: 0.0106 | E45: 285541 | G45: 285541 | I45: $ -
A46: 41 | B46: 7°C - 360 | C46: CASTRO | D46: 0.0108 | E46: 290161 | G46: $ - | I46: 290161
A47: 42 | B47: 7°B - 360 | C47: DEL RIO ANDREA | D47: 0.0161 | E47: 400724 | G47: 400724 | I47: $ -
A48: 43 | B48: 8°A - 356 | C48: SIMON PABLO | D48: 0.0192 | E48: 465261 | G48: 465261 | I48: $ -
A49: 44 | B49: 8°C - 356 | C49: RAAD J. F. | D49: 0.0123 | E49: 321143 | G49: 321143 | I49: $ -
A50: 45 | B50: 8°B - 356 | C50: PONZIO FACUNDO TOMAS | D50: 0.0108 | E50: 289730 | G50: $ - | I50: 289730
A51: 46 | B51: 8°A - 360 | C51: DURRUTY - VAZQUEZ | D51: 0.0119 | E51: 312766 | G51: 312766 | I51: $ -
A52: 47 | B52: 8°C - 360 | C52: CICCONE-ROSSI | D52: 0.0138 | E52: 352557 | G52: $ - | I52: 352557
A53: 48 | B53: 8°B - 360 | C53: MALLAMACE MARTA | D53: 0.0155 | E53: 388159 | G53: 388159 | I53: $ -
A54: 49 | B54: 9°A - 356 | C54: CALONGE RICARDO | D54: 0.0191 | E54: -1566449 | G54: $ - | I54: -1566449
A55: 50 | B55: 9°B - 356 | C55: TOSAR | D55: 0.0117 | E55: 308578 | G55: 308578 | I55: $ -
A56: 51 | B56: 9°A - 360 | C56: FAPSA | D56: 0.0117 | E56: 308200 | G56: 124000 | I56: 184200
A57: 52 | B57: 9°B - 360 | C57: FAPSA | D57: 0.0197 | E57: 476116 | G57: 476116 | I57: $ -
A58: 53 | B58: 10°A - 356 | C58: RICCI - ROLDAN | D58: 0.0186 | E58: 453080 | G58: 453080 | I58: $ -
A59: 54 | B59: 10°B - 356 | C59: PRIMAVERA | D59: 0.0102 | E59: 537214 | G59: 537214 | I59: $ -
A60: 55 | B60: 10°A - 360 | C60: MARTYNIUK | D60: 0.0102 | E60: 277164 | G60: 170064 | I60: 107100
A61: 56 | B61: 10°B - 360 | C61: GINES DEBORA | D61: 0.0172 | E61: 423761 | G61: 423761 | I61: $ -
A62: 57 | B62: 11°A - 356 | C62: ASSETTA ANA MARIA | D62: 0.0193 | E62: 467739 | G62: 467739 | I62: $ -
A63: 58 | B63: 11°B - 356 | C63: PRIMAVERA | D63: 0.0105 | E63: 283447 | G63: 283447 | I63: $ -
A64: 59 | B64: 11°A - 360 | C64: MARTYNIUK | D64: 0.0103 | E64: 279259 | G64: $ - | I64: 279259
A65: 60 | B65: 11°B - 360 | C65: VILLAR | D65: 0.0186 | E65: 1721303 | G65: 453080 | I65: 1268223
A66: 61 | B66: 12°A - 356 | C66: FERNANDEZ | D66: 0.0176 | E66: 432137 | G66: 432137 | I66: $ -
A67: 62 | B67: 12°B - 356 | C67: LAGANA OSCAR | D67: 0.0103 | E67: 279259 | G67: 279259 | I67: $ -
A68: 63 | B68: 12°A - 360 | C68: VILELA | D68: 0.0102 | E68: 277164 | G68: 277164 | I68: $ -
A69: 64 | B69: 12°B - 360 | C69: MARTINIELLO | D69: 0.0193 | E69: 467739 | G69: 467739 | I69: $ -
A70: 65 | B70: 13°A - 356 | C70: GAVELINI FEDERICO | D70: 0.0173 | E70: 425855 | G70: 425855 | I70: $ -
A71: 66 | B71: 13°B - 356 | C71: SEDAME | D71: 0.0102 | E71: 277164 | G71: 277164 | I71: $ -
A72: 67 | B72: 13°A - 360 | C72: BRUNO SANDRA | D72: 0.0102 | E72: 277164 | G72: 277164 | I72: $ -
A73: 68 | B73: 13°B - 360 | C73: QUENARDELLE | D73: 0.0169 | E73: 417478 | G73: 417478 | I73: $ -
A74: 69 | B74: 14°A - 356 | C74: VELAYOS CELINA | D74: 0.0413 | E74: 928470 | G74: 928470 | I74: $ -
A75: 70 | B75: 14°A - 360 | C75: STEVEN PUTZ | D75: 0.0413 | E75: 928470 | G75: 928470 | I75: $ -
C76: TOTALES | D76: 0.9979 | E76: 26294902 | G76: 23940465 | I76: 2354437
A78: Estado de propietarios morosos
A79: UF | B79: DEPTO | C79: CONSORCISTA | D79: DEUDA
A80: 1 | B80: 1°A - 356 | C80: SEVERINO | D80: 1587
A81: 5 | B81: 1°C - 360 | C81: BONFANTI SANDRA | D81: 2477
A82: 17 | B82: 3°C - 360 | C82: MUSACCHIO | D82: 351033
A83: 26 | B83: 5°C - 356 | C83: LANATI | D83: 421686
A84: 30 | B84: 5°B - 360 | C84: JAIMES MARISA | D84: 464017
A85: 41 | B85: 7°C - 360 | C85: CASTRO | D85: 313083
A86: 45 | B86: 8°B - 356 | C86: PONZIO FACUNDO TOMAS | D86: 312618
A87: 47 | B87: 8°C - 360 | C87: CICCONE-ROSSI | D87: 380409
A88: 51 | B88: 9°A - 360 | C88: FAPSA | D88: 198752
A89: 55 | B89: 10°A - 360 | C89: MARTYNIUK | D89: 115561
A90: 59 | B90: 11°A - 360 | C90: MARTYNIUK | D90: 301320
A91: 60 | B91: 11°B - 360 | C91: VILLAR | D91: 1368413
C92: TOTAL | D92: 4230956
A95: GASTOS ORDINARIOS DEL PERÍODO (SUMINISTROS, SERVICIOS, ABONOS Y SEGUROS)
A96: REMUNERACIONES DEL PERSONAL | E96: GASTOS COMUNES | I96: % DEL GASTO TOTAL
A97: BUSTAMANTE JUAN MANUEL - ENCARGADO PERMANTENTE SIN VIVIENDA 4ta CATEGORIA.
A98: CUIL: 20-13606437-2 - MES LIQUIDADO: FEBRERO 2026
A100: SUELDO/ JORNAL | C100: 953961
A101: ANTIGÜEDAD | C101: 228950.4
A102: ADICICIONAL FEB-26 | C102: 120000
A103: RETIRO DE RESIDUOS | C103: 122990
A104: PLUS LIMPIEZA COCHERA | C104: 23977.4
...

Sheet CUOTA SINDICAL

Sheet COMISIONES

Sheet 25413

Sheet LA UNION E HIJOS

Sheet DIFERENCIAS ENCONTRADAS
A1: DIFERENCIAS ENTRE LO LOQUIDADO Y LO REALMENTE ABONADO
A2: FECHA | B2: DETALLE | C2: PAGO REALIZADO | D2: EN LIQUIDACIÓN | E2: DIF | F2: OBSERVACION
A3: 46361 | B3: SUELDO JUAN | C3: ='12.2025'!L113 -> #REF! | D3: 1089415 | E3: =C3-D3 -> #REF! | F3: IMPORTE DEVENGADO NO REAL (LIQUIDACION MES ANTERIOR $ 1,054,813.41)
A4: 46361 | B4: SUELDO JAVIER | C4: ='12.2025'!L132 -> #REF! | D4: 681302 | E4: =C4-D4 -> #REF! | F4: IMPORTE DEVENGADO NO REAL (LIQUIDACION MES ANTERIOR $ 662,491.25) SE DEPOSITARON 20000 DE MAS
A5: 46361 | B5: SUELDO RAMIREZ | C5: ='12.2025'!L148 -> #REF! | D5: 688435 | E5: =C5-D5 -> #REF! | F5: IMPORTE DEVENGADO NO REAL (LIQUIDACION MES ANTERIOR $ 745,574.00) SE DEPOSITARON 58023 DE MENOS
A6: 46374 | B6: AGUINALDO JUAN | C6: ='12.2025'!L114 -> #REF! | D6: 1287347 | E6: =C6-D6 -> #REF! | F6: IMPORTE LIQUIDADO EN EL MES ANTERIOR CON PROVISION TOTAL MENOR AL REAL - AUNQUE EL PAGO CORRESPONDE LA RECAUDACION FUE MENOR
A7: 46374 | B7: AGUINALDO JAVIER | C7: ='12.2025'!L133 -> #REF! | D7: 0 | E7: =C7-D7 -> #REF! | F7: IMPORTE LIQUIDADO EN EL MES ANTERIOR CON PROVISION TOTAL MENOR AL REAL - AUNQUE EL PAGO CORRESPONDE LA RECAUDACION FUE MENOR
A8: 46374 | B8: AGUINALDO RAMIREZ | C8: ='12.2025'!L149 -> #REF! | D8: 0 | E8: =C8-D8 -> #REF! | F8: IMPORTE LIQUIDADO EN EL MES ANTERIOR CON PROVISION TOTAL MENOR AL REAL - AUNQUE EL PAGO CORRESPONDE LA RECAUDACION FUE MENOR
A9: 46368 | B9: CARGAS SOCIALES | C9: ='12.2025'!L153 -> #REF! | D9: ='12.2025'!F153 -> #REF! | E9: =C9-D9 -> #REF! | F9: IMPORTE DEVENGADO NO REAL (LIQUIDACION MES ANTERIOR $ 1,546,772.50)
A10: 46368 | B10: FED ARG DE TRAB | C10: 15578.92 | D10: 679584.04 | E10: =C10-D10 -> -664005.12 | F10: IMPORTE DEVENGADO NO REAL (LIQUIDACION MES ANTERIOR CON COMPROBANTES EN EL MES ANTERIOR)
A11: 46368 | B11: SIND UN TRAB REN | C11: 140210.29 | D11: 0 | E11: =C11-D11 -> 140210.29 | F11: IMPORTE DEVENGADO NO REAL (LIQUIDACION MES ANTERIOR CON COMPROBANTES EN EL MES ANTERIOR)
A12: 46368 | B12: FED ARG TRAB REN | C12: 255053.93 | D12: 0 | E12: =C12-D12 -> 255053.93 | F12: IMPORTE DEVENGADO NO REAL (LIQUIDACION MES ANTERIOR CON COMPROBANTES EN EL MES ANTERIOR)
A13: LA UNION E HIJOS SRL | B13: COMPRA DE PINTURA CUOATA 01/02 | C13: 1360711.4 | D13: 3500000 | E13: =C13-D13 -> -2139288.6 | F13: SE LIQUIDO UN GASTO EXTRAORDINARIO MUY SUPERIOR A LO FINALMENTE FACTURADO Y ESTA RECAUDACIÓN NO FUE INCLUIDA EN EL RESUMEN DE FDR QUE IBAN DESTINADOS A PINTURA, MIENTRAS QUE LOS GASTOS SI ESTAN DETALLADOS.
A14: 46368 | B14: CLEANNIG SERVICE - MATERIALES DE LIMPIEZA | C14: 175845 | D14: 212900 | E14: =C14-D14 -> -37055 | F14: SEGUN ESTO SE ABONO POR MENOS, AUNQUE EL COMPROBANTE NO ES VÁLIDO COMO FACTURA. TENEMOS LA FACTURA?
A15: 46361 | B15: SEGURIDAD NOVIEMBRE 2025 FACTURA N° 00002-0044 | C15: 2372281.2 | D15: 3704325 | E15: =D15-C15 -> 1332043.8 | F15: IMPORTE DEVENGADO NO REAL (LIQUIDACION MES ANTERIOR CON COMPROBANTES EN EL MES ANTERIOR)
A17: LIQUIDADO SIN PAGO REGISTRADO EN CUENTA
A18: YPF CICLOS | B18: COMPRA DE COMBUSTIBLE FACT Nro 00011-53269 | C18: 32000.04 | D18: COMPROBANTE CON FECHA 14/10 21:25
A19: YPF CICLOS | B19: COMPRA DE COMBUTIBLR FACT.Nro 0001-53270 | C19: 32000.04 | D19: COMPROBANTE CON FECHA 14/10 21:27
A20: ASCENSORES GUILLEMI | B20: Mantenimiento ascensores DICIEMBRE | C20: 87866.77 | D20: FACTURA DE 120000 FECHA 5/1
A21: FOTOCOPIAS DE EXPENSAS NOVIEMBRE | C21: 18900 | D21: SIN COMPROBANTE
A23: PAGO REGISTRADOS QUE NO FIGURAN EN ESTRACTO Y SI CONSIDERA LA ADMINISTRACIÓN
B24: CALOGNE RICARDO | C24: 9°A - 356 | D24: 65000
A26: GASTOS NO LIQUIDADOS QUE FUERON DEBITADOS DE CUENTA
A27: 46361 | B27: RAFAEL MOREL ROMAN | C27: 700000 | D27: CON RECIBI FECHA 5/12 | E27: PUESTO EN ESE RESUMEN DE FDR MAL COMPUTADO
A28: 46368 | B28: LUIS DE LA PAS PAVON | C28: 160000 | D28: SIN NINGUN COMPROBANTE EN ESTE MES | E28: ENTIENDO QUE PAGARON LA DIFERENCIA LIQUIDADA EL MES PASADO EN ESTE MES SALDANDO EL ERROR MARCADO EL MES ANTERIOR
A29: 46368 | B29: RAFAEL MOREL ROMAN | C29: 1000000 | D29: CON RECIBI FECHA 12/12 | E29: PUESTO EN ESE RESUMEN DE FDR MAL COMPUTADO
A30: 46374 | B30: RAFAEL MOREL ROMAN | C30: 1700000 | D30: CON RECIBI FECHA 18/12 | E30: PUESTO EN ESE RESUMEN DE FDR MAL COMPUTADO
A31: 46378 | B31: RAFAEL MOREL ROMAN | C31: 1500000 | D31: CON RECIBI FECHA 29/12 | E31: PUESTO EN ESE RESUMEN DE FDR MAL COMPUTADO
